.class public hepial
.super java/lang/Object
.method public <init>()V
aload_0
invokespecial java/lang/Object/<init>()V
return
.end method
.method public static carre(I)I
.limit stack 4
.limit locals 8
iload 0
iload 0
imul
istore 0
iload 0
ireturn
.end method
.method public static main([Ljava/lang/String;)V
.limit stack 8
.limit locals 16
ldc 3
istore 1
iload 1
invokestatic hepial.carre(I)I
ldc 1
iadd
getstatic java/lang/System/out Ljava/io/PrintStream;
swap
invokevirtual java/io/PrintStream/print(I)V
iload 1
getstatic java/lang/System/out Ljava/io/PrintStream;
swap
invokevirtual java/io/PrintStream/print(I)V
return
.end method
